one_lin3r/__init__.py
one_lin3r/main.py
one_lin3r/core/Cli.py
one_lin3r/core/__init__.py
one_lin3r/core/color.py
one_lin3r/core/db.py
one_lin3r/core/utils.py
one_lin3r/core/liners/__init__.py
one_lin3r/core/liners/example
one_lin3r/core/liners/linux/__init__.py
one_lin3r/core/liners/linux/awk/__init__.py
one_lin3r/core/liners/linux/awk/bind_tcp.py
one_lin3r/core/liners/linux/awk/reverse_tcp.py
one_lin3r/core/liners/linux/awk/reverse_udp.py
one_lin3r/core/liners/linux/bash/__init__.py
one_lin3r/core/liners/linux/bash/exploit_docker_bash_container.py
one_lin3r/core/liners/linux/bash/exploit_writeable_sudoers.py
one_lin3r/core/liners/linux/bash/find_suid.py
one_lin3r/core/liners/linux/bash/get_last_edited_files.py
one_lin3r/core/liners/linux/bash/list_all_capabilities.py
one_lin3r/core/liners/linux/bash/list_cronjobs_for_all_users.py
one_lin3r/core/liners/linux/bash/list_cronjobs_for_another_user.py
one_lin3r/core/liners/linux/bash/list_cronjobs_for_current_user.py
one_lin3r/core/liners/linux/bash/list_systemd_timers.py
one_lin3r/core/liners/linux/bash/reverse_tcp.py
one_lin3r/core/liners/linux/bash/reverse_tcp_exec.py
one_lin3r/core/liners/linux/bash/search_for_password_in_memory.py
one_lin3r/core/liners/linux/bash/search_for_password_using_find.py
one_lin3r/core/liners/linux/bash/search_for_password_using_grep.py
one_lin3r/core/liners/linux/go/__init__.py
one_lin3r/core/liners/linux/go/reverse_tcp.py
one_lin3r/core/liners/linux/java/__init__.py
one_lin3r/core/liners/linux/java/reverse_tcp.py
one_lin3r/core/liners/linux/lua/__init__.py
one_lin3r/core/liners/linux/lua/reverse_tcp.py
one_lin3r/core/liners/linux/lua/reverse_tcp_bash.py
one_lin3r/core/liners/linux/nc/__init__.py
one_lin3r/core/liners/linux/nc/bind_tcp.py
one_lin3r/core/liners/linux/nc/bind_tcp_mkfifo.py
one_lin3r/core/liners/linux/nc/reverse_tcp.py
one_lin3r/core/liners/linux/nc/reverse_tcp_mkfifo.py
one_lin3r/core/liners/linux/nc/reverse_tcp_mknod.py
one_lin3r/core/liners/linux/nc/reverse_udp.py
one_lin3r-2.0.dist-info/LICENSE
one_lin3r-2.0.dist-info/METADATA
one_lin3r-2.0.dist-info/WHEEL
one_lin3r-2.0.dist-info/entry_points.txt
one_lin3r-2.0.dist-info/top_level.txt
one_lin3r-2.0.dist-info/RECORD
