Metadata-Version: 2.1
Name: one-lin3r
Version: 2.0
Summary: One-Lin3r is simple modular and light-weight framework gives you all the one-liners that you will need while penetration testing (Windows, Linux, macOS or even BSD systems) or hacking generally with a lot of new features to make all of this fully automated (ex: you won't even need to copy the one-liners).
Home-page: https://github.com/D4Vinci/One-Lin3r
Author: Karim Shoair (D4Vinci)
Author-email: karim.shoair@pm.me
License: UNKNOWN
Platform: UNKNOWN
Classifier: Topic :: Security
Classifier: Intended Audience :: Developers
Classifier: Intended Audience :: Information Technology
Classifier: Intended Audience :: System Administrators
Classifier: Intended Audience :: Other Audience
Classifier: Natural Language :: English
Classifier: Programming Language :: Python :: 3 :: Only
Classifier: License :: Free for non-commercial use
Classifier: Operating System :: OS Independent
Requires-Dist: terminaltables
Requires-Dist: pyperclip
Requires-Dist: prompt-toolkit
Requires-Dist: win-unicode-console ; platform_system == "Windows"
Requires-Dist: colorama ; platform_system == "Windows"
